prettree/__init__.py
prettree/cli.py
prettree/core.py
prettree-0.1.1.dist-info/METADATA
prettree-0.1.1.dist-info/WHEEL
prettree-0.1.1.dist-info/entry_points.txt
prettree-0.1.1.dist-info/licenses/LICENSE
prettree-0.1.1.dist-info/RECORD
