Metadata-Version: 2.4
Name: prettree
Version: 0.1.1
Summary: A cross-platform directory tree visualization tool
Project-URL: Homepage, https://github.com/mucahitkayadan/prettree
Project-URL: Repository, https://github.com/mucahitkayadan/prettree.git
Author-email: Muja Kayadan <mujakayadan@outlook.com>
License-Expression: MIT
License-File: LICENSE
Keywords: cli,directory,filesystem,tree
Classifier: Development Status :: 3 - Alpha
Classifier: Intended Audience :: Developers
Classifier: License :: OSI Approved :: MIT License
Classifier: Programming Language :: Python :: 3
Classifier: Programming Language :: Python :: 3.7
Classifier: Programming Language :: Python :: 3.8
Classifier: Programming Language :: Python :: 3.9
Classifier: Programming Language :: Python :: 3.10
Classifier: Programming Language :: Python :: 3.11
Classifier: Programming Language :: Python :: 3.12
Classifier: Programming Language :: Python :: 3.13
Requires-Python: >=3.7
